CHANGELOG.md
codenames/__init__.py
codenames/classic/__init__.py
codenames/classic/board.py
codenames/classic/color.py
codenames/classic/player.py
codenames/classic/runner.py
codenames/classic/score.py
codenames/classic/state.py
codenames/classic/team.py
codenames/classic/types.py
codenames/classic/winner.py
codenames/duet/__init__.py
codenames/duet/board.py
codenames/duet/card.py
codenames/duet/player.py
codenames/duet/runner.py
codenames/duet/score.py
codenames/duet/state.py
codenames/duet/team.py
codenames/duet/types.py
codenames/generic/__init__.py
codenames/generic/board.py
codenames/generic/card.py
codenames/generic/exceptions.py
codenames/generic/move.py
codenames/generic/player.py
codenames/generic/runner.py
codenames/generic/state.py
codenames/generic/team.py
codenames/mini/__init__.py
codenames/mini/runner.py
codenames/mini/state.py
codenames/online/__init__.py
codenames/online/codenames_game/__init__.py
codenames/online/codenames_game/adapter.py
codenames/online/codenames_game/agent.py
codenames/online/codenames_game/card_parser.py
codenames/online/codenames_game/runner.py
codenames/online/codenames_game/screenshot.py
codenames/online/utils.py
codenames/py.typed
codenames/utils/__init__.py
codenames/utils/builder.py
codenames/utils/formatting.py
codenames/utils/game_type.py
codenames/utils/vocabulary/__init__.py
codenames/utils/vocabulary/english.py
codenames/utils/vocabulary/hebrew.py
codenames/utils/vocabulary/languages.py
codenames-5.5.5.dist-info/METADATA
codenames-5.5.5.dist-info/WHEEL
codenames-5.5.5.dist-info/RECORD
