Metadata-Version: 2.1
Name: codenames
Version: 5.5.5
Summary: Codenames board game logic implementation in python.
Author: Asaf Kali
Author-email: asaf.kali@mail.huji.ac.il
Requires-Python: >=3.12,<4.0
Classifier: Programming Language :: Python :: 3
Classifier: Programming Language :: Python :: 3.12
Provides-Extra: web
Requires-Dist: beautifultable (>=1.0,<2.0)
Requires-Dist: pydantic (>=2.0,<3.0)
Requires-Dist: selenium (>=4.1,<5.0) ; extra == "web"
Project-URL: Homepage, https://github.com/asaf-kali/codenames
Project-URL: Issues, https://github.com/asaf-kali/codenames/issues
Project-URL: Repository, https://github.com/asaf-kali/codenames
